<routes><route id="0" town="Town12">
      <weathers>
         <weather route_percentage="0.0" cloudiness="50.0" precipitation="20.0" precipitation_deposits="12.0" wetness="10.0" wind_intensity="30.0" sun_azimuth_angle="45.0" sun_altitude_angle="10.0" fog_density="0.0" />
         <weather route_percentage="100.0" cloudiness="0.0" precipitation="0.0" precipitation_deposits="50.0" wetness="0.0" wind_intensity="10.0" sun_azimuth_angle="0.0" sun_altitude_angle="90.0" fog_density="4.0" />
      </weathers>
      <waypoints>
         <position x="2745.6" y="4743.4" z="365.7" />
         <position x="2640.4" y="4678.8" z="364.7" />
         <position x="2537.8" y="4612.0" z="363.7" />
      </waypoints>
      <scenarios>
         <scenario name="VehicleTurningRoutePedestrian_3" type="VehicleTurningRoutePedestrian">
            <trigger_point x="2749.0" y="4723.2" z="365.5" yaw="279.4" />
         </scenario>
         <scenario name="DynamicObjectCrossing_14" type="DynamicObjectCrossing">
            <trigger_point x="2674.3" y="4684.3" z="364.8" yaw="189.2" />
            <distance value="35" />
            <blocker_model value="static.prop.foodcart" />
            <crossing_angle value="10" />
         </scenario>
         <scenario name="PedestrianCrossing_4" type="PedestrianCrossing">
            <trigger_point x="2595.2" y="4671.5" z="364.6" yaw="189.2" />
         </scenario>
      </scenarios>
   </route>
</routes>